Workbook

Sheet parte 1
B2: Inversion Incial (Año 0)
B3: Rubro | C3: Monto
B4: Adquisición De Terreno Para Planta (1.5 Has) | C4: 35000 | F4: Capacidad de producion mensual | I4: 23000
B5: Contrucción De La Planta De Procesamiento | C5: 180000
B6: Adquisión E Instalación De Maquinarias Y Equipos | C6: 90000
B7: Equipo De Oficina Y Comunicación | C7: 7000
B8: Camioneta De Reparto ( 3tn) | C8: 150000
B9: Certificacion De Licencias | C9: 12000
B10: Desarrollo De Proveedores Y Cadema De Frío | C10: 45000
B11: Total Inversión Fija | C11: =SUM(C4:C10) -> 519000
B12: Capital De Trabajo | C12: =C170 -> 468186.67
B13: Total De Capital De Trabajo | C13: =-C12 -> -468186.67
B14: Total De Inversión | C14: =C11+C13 -> 50813.333
B17: Costo variable Unitarios por kilogramos de pulpa procesada
B19: Rubro | C19: Unidad De Medida | D19: Valor Unitario | E19: Unidades utilizadas | F19: Costo Fijo | G19: Costo Variable | H19: Costo Total
B21: Fruta fresca (mango/maracuyá) | C21: Kg | D21: 5.5 | E21: 20 | G21: =D21*E21 -> 110 | H21: =F21+G21 -> 110
B22: Lavado y selección | C22: Kg | D22: 0.35 | E22: 1 | G22: =D22*E22 -> 0.35 | H22: =F22+G22 -> 0.35
B23: Despulpado | C23: Kg | D23: 0.55 | E23: 1 | G23: =D23*E23 -> 0.55 | H23: =F23+G23 -> 0.55
B24: Pasteurización | C24: Kg | D24: 0.45 | E24: 1 | G24: =D24*E24 -> 0.45 | H24: =F24+G24 -> 0.45
B25: Empaquetado y sellado | C25: Kg | D25: 0.35 | E25: 1 | G25: =D25*E25 -> 0.35 | H25: =F25+G25 -> 0.35
B26: Costos De Producción Mes 1 | F26: =SUM(F21:F25) -> 0 | G26: =SUM(G21:G25) -> 111.7 | H26: =SUM(H21:H25) -> 111.7
B30: Costos Operativos Primer Mes En Nuevos Soles
B32: Rubro | F32: Monto Mensual
B33: Gastos De Administración
B34: Servicios Publicos (Agua, Luz, Desague, Internet) | F34: 1200
B35: Mantenimiento De Instlaciones Y Equipos | F35: 700
B36: Personal Administrativo 2 Profesionales) | F36: 11000
B37: Personal De Producción (6 Operarios) | F37: 9000
B38: Marketin Y Publicidad Online | F38: 300
B39: Seguridad Y Vigilancia De Planta | F39: 600
B40: Gastos De Distribución De Flete Por Cliente | F40: =0.3*I4 -> 6900
B41: Total Costos Operativos | F41: =SUM(F34:F40) -> 29700
B46: Costo Unitario
B48: Precio de venta | C48: 32
B54: Rubro | C54: 0 | D54: 1 | E54: 2 | F54: 3 | G54: 4 | H54: 5 | I54: 6 | J54: 7 | K54: 8 | L54: 9 | M54: 10 | N54: 11 | O54: 12
B55: Ventas en kilogramos | D55: 1200 | E55: 1400 | F55: 1500 | G55: 17000 | H55: 1800 | I55: 1800 | J55: 1700 | K55: 1600 | L55: 1900 | M55: 2000 | N55: 2100 | O55: 2200
B56: Precio De Venta (Por Unidad) | D56: =C48 -> 32 | E56: =D56 -> 32 | F56: =E56 -> 32 | G56: =F56 -> 32 | H56: =G56 -> 32 | I56: =H56 -> 32 | J56: =I56 -> 32 | K56: =J56 -> 32 | L56: =K56 -> 32 | ... O56: =N56 -> 32
B59: Tabla De Depreciaciones
B60: Activos | C60: Valor Compra | D60: Vida Util | E60: Dep Anual (1-6) | F60: Dep Anual (7-12) | G60: Dep Acumulada | H60: Valor De Recupero
B61: ='parte 1'!B5 -> Contrucción De La Planta De Procesamiento | C61: ='parte 1'!C5 -> 180000 | D61: 30 | E61: =C61*(1/D61) -> 6000 | F61: =E61 -> 6000 | G61: =E61*12 -> 72000 | H61: =C61-G61 -> 108000
B62: ='parte 1'!B6 -> Adquisión E Instalación De Maquinarias Y Equipos | C62: ='parte 1'!C6 -> 90000 | D62: 8 | E62: =C62*(1/D62) -> 11250 | F62: =E62 -> 11250 | G62: =E62*12 -> 135000 | H62: =C62-G62 -> -45000
B63: =B8 -> Camioneta De Reparto ( 3tn) | C63: =C8 -> 150000 | D63: 5 | E63: =C63*(1/D63) -> 30000 | F63: =E63 -> 30000 | G63: =E63*12 -> 360000 | H63: =C63-G63 -> -210000
B64: =B7 -> Equipo De Oficina Y Comunicación | C64: =C7 -> 7000 | D64: 4 | E64: =C64*(1/D64) -> 1750 | F64: =E64 -> 1750 | G64: =E64*12 -> 21000 | H64: =C64-G64 -> -14000
B65: Total | E65: =SUM(E61:E64) -> 49000 | F65: =SUM(F61:F64) -> 49000 | G65: =SUM(G61:G64) -> 588000 | H65: =SUM(H61:H64) -> -161000
B69: SOLUCIÓN
B71: a)
B73: COSTO TOTAL | C73: =H26+F41 -> 29811.7
B75: b)
B77: Rubro | C77: 0 | D77: 1 | E77: 2 | F77: 3 | G77: 4 | H77: 5 | I77: 6 | J77: 7 | K77: 8 | L77: 9 | M77: 10 | N77: 11 | O77: 12 | P77: Año 1
B78: Ventas en soles | D78: =D55*D56 -> 38400 | E78: =E55*E56 -> 44800 | F78: =F55*F56 -> 48000 | G78: =G55*G56 -> 544000 | H78: =H55*H56 -> 57600 | I78: =I55*I56 -> 57600 | J78: =J55*J56 -> 54400 | K78: =K55*K56 -> 51200 | ... O78: =O55*O56 -> 70400 | P78: =SUM(D78:O78) -> 1158400
B80: c)
B82: CAPITAL DE TRABAJO
B85: RUBRO | C85: Años 1 | D85: Año 2 | E85: Año 3 | F85: Año 4
B86: Caja mínima (dias de venta ) | C86: 15 | D86: =C86 -> 15 | E86: =D86 -> 15 | F86: =E86 -> 15
B87: CuentasXCobras (días promedio) | C87: 150 | D87: =C87 -> 150 | E87: =D87 -> 150 | F87: =E87 -> 150
B88: Inventarios (dias promedio) | C88: 60 | D88: =C88 -> 60 | E88: =D88 -> 60 | F88: =E88 -> 60
B89: Proveedores (Cuentas por pagar - dias promedio) | C89: 90 | D89: =C89 -> 90 | E89: =D89 -> 90 | F89: =E89 -> 90
B91: INGRESOS Y EGRESOS DEL NEGOCIO
B93: RUBRO | C93: Años 1 | D93: Año 2 | E93: Año 3 | F93: Año 4
B94: Ventas proyectadas (S/.) | C94: =P78 -> 1158400 | D94: =C94 -> 1158400 | E94: =D94 -> 1158400 | F94: =E94 -> 1158400
B95: Costos de venta (% sobre ventas) | C95: 0.65 | D95: 0.65 | E95: 0.65 | F95: 0.66
B96: Gastos operativos (% sobre ventas) | C96: 0.15 | D96: 0.15 | E96: 0.15 | F96: 0.16
B97: Depreciación anual | C97: =G65 -> 588000 | D97: =C97 -> 588000 | E97: =D97 -> 588000 | F97: =E97 -> 588000
B99: KW = Caja + CxC + Inventario - Proveedores
B101: CAJA:
B103: Año 1 = | C103: Ventas año 1 | D103: x 2
C104: 360
B106: Año 1 = | C106: =C94*C86/360 -> 48266.667 | D106: soles
B107: Año 2= | C107: =D94*D86/360 -> 48266.667 | D107: soles
B108: Año 3 = | C108: =E94*E86/360 -> 48266.667 | D108: soles
B110: CUENTAS X COBRAR
B112: Rotación de CC = | C112: CxC | D112: x360
C113: Ventas
B115: CxC = | C115: Rotación de CC x Ventas
C116: 360
B118: Año 1 | C118: =C87*C94/360 -> 482666.67 | D118: soles
B119: Año 2 | C119: =D87*D94/360 -> 482666.67 | D119: soles
B120: Año 3 | C120: =E87*E94/360 -> 482666.67 | D120: soles
B122: INVENTARIOS
B124: Rotación Inventarios = | C124: Inventarios | D124: x360
C125: Costos Ventas
B127: Inventarios = | C127: Rotación Inventarios x Costos Ventas
C128: 360
B130: Año 1= | C130: =C88*C94*C95/360 -> 125493.33 | D130: soles
B131: Año 2= | C131: =D88*D94*D95/360 -> 125493.33 | D131: soles
B132: Año 3= | C132: =E88*E94*E95/360 -> 125493.33 | D132: soles
B134: PROVEEDORES - Cuentas x Pagar
B136: Rotación CxP= | C136: CxP | D136: x 360
C137: Costos Ventas
B139: CxP = | C139: Rotación CxP x Costos Ventas
C140: 360
B142: Año 1= | C142: =C89*C94*C95/360 -> 188240 | D142: soles
B143: Año 2= | C143: =D89*D94*D95/360 -> 188240 | D143: soles
B144: Año 3= | C144: =E89*E94*E95/360 -> 188240 | D144: soles
B147: Situación Financiera Año 1
B148: Caja | C148: =C106 -> 48266.667 | D148: Proveedores | E148: =C142 -> 188240
B149: Cuentas x Cobrar | C149: =C118 -> 482666.67
B150: Inventarios | C150: =C130 -> 125493.33
B151: KWN año 1 | C151: =C148+C149+C150-E148 -> 468186.67
B153: Situación Financiera Año 2
...

Sheet parte 2
B2: Inversion Incial (Año 0)
B3: Rubro | C3: Monto
B4: Adquisición De Terreno Para Planta (1.5 Has) | C4: 35000 | F4: Capacidad de producion mensual | I4: 23000
B5: Contrucción De La Planta De Procesamiento | C5: 180000
B6: Adquisión E Instalación De Maquinarias Y Equipos | C6: 90000
B7: Equipo De Oficina Y Comunicación | C7: 7000
B8: Camioneta De Reparto ( 3tn) | C8: 150000
B9: Certificacion De Licencias | C9: 12000
B10: Desarrollo De Proveedores Y Cadema De Frío | C10: 45000
B11: Terreno | C11: 30000
B12: Almacen | C12: 80000
B13: Total Inversión Fija | C13: =SUM(C4:C10) -> 519000
B14: Capital De Trabajo | C14: ='parte 2'!C112 -> -28000
B15: Total De Capital De Trabajo | C15: =-C14 -> 28000
B16: Total De Inversión | C16: =C13+C15 -> 547000
B19: Costo variable Unitarios por kilogramos de pulpa procesada
B21: Rubro | C21: Unidad De Medida | D21: Valor Unitario | E21: Unidades utilizadas | F21: Costo Fijo | G21: Costo Variable | H21: Costo Total
B23: Fruta fresca (mango/maracuyá) | C23: Kg | D23: 5.5 | E23: 20 | G23: =D23*E23 -> 110 | H23: =F23+G23 -> 110
B24: Lavado y selección | C24: Kg | D24: 0.35 | E24: 1 | G24: =D24*E24 -> 0.35 | H24: =F24+G24 -> 0.35
B25: Despulpado | C25: Kg | D25: 0.55 | E25: 1 | G25: =D25*E25 -> 0.55 | H25: =F25+G25 -> 0.55
B26: Pasteurización | C26: Kg | D26: 0.45 | E26: 1 | G26: =D26*E26 -> 0.45 | H26: =F26+G26 -> 0.45
B27: Empaquetado y sellado | C27: Kg | D27: 0.35 | E27: 1 | G27: =D27*E27 -> 0.35 | H27: =F27+G27 -> 0.35
B28: Costos De Producción Mes 1 | F28: =SUM(F23:F27) -> 0 | G28: =SUM(G23:G27) -> 111.7 | H28: =SUM(H23:H27) -> 111.7
B32: Costos Operativos Primer Mes En Nuevos Soles
B34: Rubro | F34: Monto Mensual
B35: Gastos De Administración
B36: Servicios Publicos (Agua, Luz, Desague, Internet) | F36: 1200
B37: Mantenimiento De Instlaciones Y Equipos | F37: 700
B38: Personal Administrativo 2 Profesionales) | F38: 11000
B39: Personal De Producción (6 Operarios) | F39: 9000
B40: Marketin Y Publicidad Online | F40: 300
B41: Seguridad Y Vigilancia De Planta | F41: 600
B42: Gastos De Distribución De Flete Por Cliente | F42: =0.3*I4 -> 6900
B43: Total Costos Operativos | F43: =SUM(F36:F42) -> 29700
B48: Costo Unitario
B50: Precio de venta | C50: 32
B56: Rubro | C56: 0 | D56: 1 | E56: 2 | F56: 3 | G56: 4 | H56: 5 | I56: 6 | J56: 7 | K56: 8 | L56: 9 | M56: 10 | N56: 11 | O56: 12
B57: Ventas en kilogramos | D57: 1200 | E57: 1400 | F57: 1500 | G57: 17000 | H57: 1800 | I57: 1800 | J57: 1700 | K57: 1600 | L57: 1900 | M57: 2000 | N57: 2100 | O57: 2200
B58: Precio De Venta (Por Unidad) | D58: =C50 -> 32 | E58: =D58 -> 32 | F58: =E58 -> 32 | G58: =F58 -> 32 | H58: =G58 -> 32 | I58: =H58 -> 32 | J58: =I58 -> 32 | K58: =J58 -> 32 | L58: =K58 -> 32 | ... O58: =N58 -> 32
B61: Tabla De Depreciaciones
B62: Activos | C62: Valor Compra | D62: Vida Util | E62: Dep Anual (1-6) | F62: Dep Anual (7-12) | G62: Dep Acumulada | H62: Valor De Recupero
B63: ='parte 2'!B5 -> Contrucción De La Planta De Procesamiento | C63: ='parte 2'!C5 -> 180000 | D63: 30 | E63: =C63*(1/D63) -> 6000 | F63: =E63 -> 6000 | G63: =E63*12 -> 72000 | H63: =C63-G63 -> 108000
B64: ='parte 2'!B6 -> Adquisión E Instalación De Maquinarias Y Equipos | C64: ='parte 2'!C6 -> 90000 | D64: 8 | E64: =C64*(1/D64) -> 11250 | F64: =E64 -> 11250 | G64: =E64*12 -> 135000 | H64: =C64-G64 -> -45000
B65: =B8 -> Camioneta De Reparto ( 3tn) | C65: =C8 -> 150000 | D65: 5 | E65: =C65*(1/D65) -> 30000 | F65: =E65 -> 30000 | G65: =E65*12 -> 360000 | H65: =C65-G65 -> -210000
B66: =B7 -> Equipo De Oficina Y Comunicación | C66: =C7 -> 7000 | D66: 4 | E66: =C66*(1/D66) -> 1750 | F66: =E66 -> 1750 | G66: =E66*12 -> 21000 | H66: =C66-G66 -> -14000
B67: =B12 -> Almacen | C67: =C12 -> 80000 | D67: 30 | E67: =C67*(1/D67) -> 2666.6667 | F67: =E67 -> 2666.6667 | G67: =E67*12 -> 32000 | H67: =C67-G67 -> 48000
B68: Total | E68: =SUM(E63:E66) -> 49000 | F68: =SUM(F63:F66) -> 49000 | G68: =SUM(G63:G66) -> 588000 | H68: =SUM(H63:H66) -> -161000
B73: Estado De Resultados Con Depreciaciones
B74: Rubro | C74: 0 | D74: 1 | E74: 2 | F74: 3 | G74: 4 | H74: 5 | I74: 6 | J74: 7 | K74: 8 | L74: 9 | M74: 10
B75: Ventas Netas | D75: ='parte 2'!D57*'parte 2'!D58 -> 38400 | E75: ='parte 2'!E57*'parte 2'!E58 -> 44800 | F75: ='parte 2'!F57*'parte 2'!F58 -> 48000 | G75: ='parte 2'!G57*'parte 2'!G58 -> 544000 | H75: ='parte 2'!H57*'parte 2'!H58 -> 57600 | I75: ='parte 2'!I57*'parte 2'!I58 -> 57600 | J75: ='parte 2'!J57*'parte 2'!J58 -> 54400 | K75: ='parte 2'!K57*'parte 2'!K58 -> 51200 | ... M75: ='parte 2'!M57*'parte 2'!M58 -> 64000
B76: Costo Variable | D76: ='parte 2'!D57*30 -> 36000 | E76: ='parte 2'!E57*30 -> 42000 | F76: ='parte 2'!F57*30 -> 45000 | G76: ='parte 2'!G57*30 -> 510000 | H76: ='parte 2'!H57*30 -> 54000 | I76: ='parte 2'!I57*30 -> 54000 | J76: ='parte 2'!J57*30 -> 51000 | K76: ='parte 2'!K57*30 -> 48000 | ... M76: ='parte 2'!M57*30 -> 60000
B77: Costo Fijo | D77: 20000 | E77: 20000 | F77: 20000 | G77: 20000 | H77: 20000 | I77: 20000 | J77: 20000 | K77: 20000 | L77: 20000 | M77: 20000
B78: Depreciaciones | D78: ='parte 2'!E68 -> 49000 | E78: =D78 -> 49000 | F78: =E78 -> 49000 | G78: =F78 -> 49000 | H78: =G78 -> 49000 | I78: =H78 -> 49000 | J78: =I78 -> 49000 | K78: =J78 -> 49000 | L78: =K78 -> 49000 | M78: =L78 -> 49000
B80: Utilidad Imponible | D80: =D75-D76-D77-D78 -> -66600 | E80: =E75-E76-E77-E78 -> -66200 | F80: =F75-F76-F77-F78 -> -66000 | G80: =G75-G76-G77-G78 -> -35000 | H80: =H75-H76-H77-H78 -> -65400 | I80: =I75-I76-I77-I78 -> -65400 | J80: =J75-J76-J77-J78 -> -65600 | K80: =K75-K76-K77-K78 -> -65800 | ... M80: =M75-M76-M77-M78 -> -65000
B81: Impuetos | D81: =D80*17% -> -11322 | E81: =E80*17% -> -11254 | F81: =F80*17% -> -11220 | G81: =G80*17% -> -5950 | H81: =H80*17% -> -11118 | I81: =I80*17% -> -11118 | J81: =J80*17% -> -11152 | K81: =K80*17% -> -11186 | ... M81: =M80*17% -> -11050
B82: Utilidad Neta | D82: =D80-D81 -> -55278 | E82: =E80-E81 -> -54946 | F82: =F80-F81 -> -54780 | G82: =G80-G81 -> -29050 | H82: =H80-H81 -> -54282 | I82: =I80-I81 -> -54282 | J82: =J80-J81 -> -54448 | K82: =K80-K81 -> -54614 | ... M82: =M80-M81 -> -53950
B84: Estado De Resultados Sin Depreciaciones
B85: Rubro | C85: 0 | D85: 1 | E85: 2 | F85: 3 | G85: 4 | H85: 5 | I85: 6 | J85: 7 | K85: 8 | L85: 9 | M85: 10
B86: Ventas Netas | D86: =D75 -> 38400 | E86: =E75 -> 44800 | F86: =F75 -> 48000 | G86: =G75 -> 544000 | H86: =H75 -> 57600 | I86: =I75 -> 57600 | J86: =J75 -> 54400 | K86: =K75 -> 51200 | ... M86: =M75 -> 64000
B87: Costo Variable | D87: =D76 -> 36000 | E87: =E76 -> 42000 | F87: =F76 -> 45000 | G87: =G76 -> 510000 | H87: =H76 -> 54000 | I87: =I76 -> 54000 | J87: =J76 -> 51000 | K87: =K76 -> 48000 | ... M87: =M76 -> 60000
B88: Costo Fijo | D88: =D77 -> 20000 | E88: =E77 -> 20000 | F88: =F77 -> 20000 | G88: =G77 -> 20000 | H88: =H77 -> 20000 | I88: =I77 -> 20000 | J88: =J77 -> 20000 | K88: =K77 -> 20000 | ... M88: =M77 -> 20000
B89: Depreciaciones | E89: =D89 -> 0 | F89: =E89 -> 0 | G89: =F89 -> 0 | H89: =G89 -> 0 | I89: =H89 -> 0 | J89: =I89 -> 0 | K89: =J89 -> 0 | L89: =K89 -> 0 | M89: =L89 -> 0
B91: Utilidad Imponible | D91: =D86-D87-D88-D89 -> -17600 | E91: =E86-E87-E88-E89 -> -17200 | F91: =F86-F87-F88-F89 -> -17000 | G91: =G86-G87-G88-G89 -> 14000 | H91: =H86-H87-H88-H89 -> -16400 | I91: =I86-I87-I88-I89 -> -16400 | J91: =J86-J87-J88-J89 -> -16600 | K91: =K86-K87-K88-K89 -> -16800 | ... M91: =M86-M87-M88-M89 -> -16000
B92: Impuetos (Se Va Con El E°) | D92: =D91*17% -> -2992 | E92: =E91*17% -> -2924 | F92: =F91*17% -> -2890 | G92: =G91*17% -> 2380 | H92: =H91*17% -> -2788 | I92: =I91*17% -> -2788 | J92: =J91*17% -> -2822 | K92: =K91*17% -> -2856 | ... M92: =M91*17% -> -2720
B93: Utilidad Neta | D93: =D91-D92 -> -14608 | E93: =E91-E92 -> -14276 | F93: =F91-F92 -> -14110 | G93: =G91-G92 -> 11620 | H93: =H91-H92 -> -13612 | I93: =I91-I92 -> -13612 | J93: =J91-J92 -> -13778 | K93: =K91-K92 -> -13944 | ... M93: =M91-M92 -> -13280
B95: 5. Amortizacion De Deuda
B96: Monto Del Prestamos | C96: 0 | D96: Endeudamiento | E96: 0
B97: Tea | C97: 0.09 | D97: Fondo Propio | E97: 10
B98: N | C98: 8
B99: Pago | C99: =-PMT(C97,C98,C96) -> 0
B101: Periodo | C101: 0 | D101: 1 | E101: 2 | F101: 3 | G101: 4 | H101: 5 | I101: 6 | J101: 7 | K101: 8
B102: Deuda Inicial | C102: =C96 -> 0 | D102: =C106 -> 0 | E102: =D106 -> 0 | F102: =E106 -> 0 | G102: =F106 -> 0 | H102: =G106 -> 0 | I102: =H106 -> 0 | J102: =I106 -> 0 | K102: =J106 -> 0
B103: Interes | C103: 0 | D103: =D102*$C$97 -> 0 | E103: =E102*$C$97 -> 0 | F103: =F102*$C$97 -> 0 | G103: =G102*$C$97 -> 0 | H103: =H102*$C$97 -> 0 | I103: =I102*$C$97 -> 0 | J103: =J102*$C$97 -> 0 | K103: =K102*$C$97 -> 0
B104: Amortizacion Del Capital | C104: 0 | D104: =D105-D103 -> 0 | E104: =E105-E103 -> 0 | F104: =F105-F103 -> 0 | G104: =G105-G103 -> 0 | H104: =H105-H103 -> 0 | I104: =I105-I103 -> 0 | J104: =J105-J103 -> 0 | K104: =K105-K103 -> 0
B105: Couta | C105: 0 | D105: =$C$99 -> 0 | E105: =$C$99 -> 0 | F105: =$C$99 -> 0 | G105: =$C$99 -> 0 | H105: =$C$99 -> 0 | I105: =$C$99 -> 0 | J105: =$C$99 -> 0 | K105: =$C$99 -> 0
B106: Deuda Final | C106: =C102 -> 0 | D106: =D102-D104 -> 0 | E106: =E102-E104 -> 0 | F106: =F102-F104 -> 0 | G106: =G102-G104 -> 0 | H106: =H102-H104 -> 0 | I106: =I102-I104 -> 0 | J106: =J102-J104 -> 0 | K106: =K102-K104 -> 0
B108: Flujo De Caja Económico Y Financiero
B110: Rubros | C110: 0 | D110: 1 | E110: 2 | F110: 3 | G110: 4 | H110: 5 | I110: 6 | J110: 7 | K110: 8 | L110: 9 | M110: 10
A111: - | B111: Activo Fijo | C111: =-'parte 2'!C13 -> -519000 | I111: =-'parte 2'!C6 -> -90000
A112: - | B112: Capital De Trabajo | C112: =((-D87-D88)/2) -> -28000 | D112: =((-E87-E88)/2-C112) -> -3000 | E112: =((-F87-F88)/2-D112-C112) -> -1500 | F112: =((-G87-G88)/2-E112-D112-C112) -> -232500 | G112: =((-H87-H88)/2-F112-E112-D112-C112) -> 228000 | H112: =((-I87-I88)/2-G112-F112-E112-D112-C112) -> 0 | I112: =((-J87-J88)/2-H112-G112-F112-E112-D112-C112) -> 1500 | J112: =((-K87-K88)/2-I112-H112-G112-F112-E112-D112-C112) -> 1500 | K112: =((-L87-L88)/2-J112-I112-H112-G112-F112-E112-D112-C112) -> -4500 | L112: =((-M87-M88)/2-K112-J112-I112-H112-G112-F112-E112-D112-C112) -> -1500
A113: + | B113: Ingreso Por Ventas De Maquinaria | I113: ='parte 2'!C6/2 -> 45000
A114: + | B114: Valor Recupero Capital De Trabajo | M114: =-SUM(C112:M112) -> 40000
A115: + | B115: Valor De Recupero De Terreno | M115: ='parte 2'!C4 -> 35000
A116: + | B116: Valor De Recupero De Activo Fijo (Vr) | M116: ='parte 2'!H68 -> -161000
B117: Flujo De Inversion Y Liquidación | C117: =SUM(C111:C116) -> -547000 | D117: =SUM(D111:D116) -> -3000 | E117: =SUM(E111:E116) -> -1500 | F117: =SUM(F111:F116) -> -232500 | G117: =SUM(G111:G116) -> 228000 | H117: =SUM(H111:H116) -> 0 | I117: =SUM(I111:I116) -> -43500 | J117: =SUM(J111:J116) -> 1500 | ... M117: =SUM(M111:M116) -> -86000
A118: + | B118: Ingreso En Efectivo | D118: =D75 -> 38400 | E118: =E75 -> 44800 | F118: =F75 -> 48000 | G118: =G75 -> 544000 | H118: =H75 -> 57600 | I118: =I75 -> 57600 | J118: =J75 -> 54400 | K118: =K75 -> 51200 | ... M118: =M75 -> 64000
A119: - | B119: Costos Fijos | D119: =-D77 -> -20000 | E119: =-E77 -> -20000 | F119: =-F77 -> -20000 | G119: =-G77 -> -20000 | H119: =-H77 -> -20000 | I119: =-I77 -> -20000 | J119: =-J77 -> -20000 | K119: =-K77 -> -20000 | ... M119: =-M77 -> -20000
A120: - | B120: Costos Variables | D120: =-D76 -> -36000 | E120: =-E76 -> -42000 | F120: =-F76 -> -45000 | G120: =-G76 -> -510000 | H120: =-H76 -> -54000 | I120: =-I76 -> -54000 | J120: =-J76 -> -51000 | K120: =-K76 -> -48000 | ... M120: =-M76 -> -60000
A121: - | B121: Impuestos Y Tibutos | D121: =-D81 -> 11322 | E121: =-E81 -> 11254 | F121: =-F81 -> 11220 | G121: =-G81 -> 5950 | H121: =-H81 -> 11118 | I121: =-I81 -> 11118 | J121: =-J81 -> 11152 | K121: =-K81 -> 11186 | ... M121: =-M81 -> 11050
B122: Flujo De Caja Operativo | D122: =SUM(D118:D121) -> -6278 | E122: =SUM(E118:E121) -> -5946 | F122: =SUM(F118:F121) -> -5780 | G122: =SUM(G118:G121) -> 19950 | H122: =SUM(H118:H121) -> -5282 | I122: =SUM(I118:I121) -> -5282 | J122: =SUM(J118:J121) -> -5448 | K122: =SUM(K118:K121) -> -5614 | ... M122: =SUM(M118:M121) -> -4950
B123: Flujo De Caja Economico (Fce) | C123: =C117+C122 -> -547000 | D123: =D117+D122 -> -9278 | E123: =E117+E122 -> -7446 | F123: =F117+F122 -> -238280 | G123: =G117+G122 -> 247950 | H123: =H117+H122 -> -5282 | I123: =I117+I122 -> -48782 | J123: =J117+J122 -> -3948 | ... M123: =M117+M122 -> -90950
B125: Financiamiento Neto
A126: + | B126: Prestamos | C126: =C96 -> 0
A127: - | B127: Capital | D127: =-D104 -> 0 | E127: =-E104 -> 0 | F127: =-F104 -> 0 | G127: =-G104 -> 0 | H127: =-H104 -> 0 | I127: =-I104 -> 0 | J127: =-J104 -> 0 | K127: =-K104 -> 0
A128: - | B128: Intereses | D128: =-D103 -> 0 | E128: =-E103 -> 0 | F128: =-F103 -> 0 | G128: =-G103 -> 0 | H128: =-H103 -> 0 | I128: =-I103 -> 0 | J128: =-J103 -> 0 | K128: =-K103 -> 0
A129: + | B129: Escudo Fiscal O Tributario | D129: =-17%*D128 -> 0 | E129: =-17%*E128 -> 0 | F129: =-17%*F128 -> 0 | G129: =-17%*G128 -> 0 | H129: =-17%*H128 -> 0 | I129: =-17%*I128 -> 0 | J129: =-17%*J128 -> 0 | K129: =-17%*K128 -> 0
B130: Flujo De Caja De Deuda | C130: =SUM(C126:C129) -> 0 | D130: =SUM(D126:D129) -> 0 | E130: =SUM(E126:E129) -> 0 | F130: =SUM(F126:F129) -> 0 | G130: =SUM(G126:G129) -> 0 | H130: =SUM(H126:H129) -> 0 | I130: =SUM(I126:I129) -> 0 | J130: =SUM(J126:J129) -> 0 | ... M130: =SUM(M126:M129) -> 0
B132: Flujo De Caja Finaciero | C132: =C123+C130 -> -547000 | D132: =D123+D130 -> -9278 | E132: =E123+E130 -> -7446 | F132: =F123+F130 -> -238280 | G132: =G123+G130 -> 247950 | H132: =H123+H130 -> -5282 | I132: =I123+I130 -> -48782 | J132: =J123+J130 -> -3948 | ... M132: =M123+M130 -> -90950
B134: Cok: Costo De Opotunidad De Capital | C134: (Es El Mínima Rentabilidad Que Exige El Inversionista Por Su Participación)
B135: Wacc: Costo Medio Ponderado Del Capital
...

Sheet preguntas
